TableProcessor/__init__.py
TableProcessor/blank.py
TableProcessor/config.py
TableProcessor/process_pipeline.py
TableProcessor/processing.py
TableProcessor/utils.py
output/__init__.py
TableProcessor-1.3.0.dist-info/METADATA
TableProcessor-1.3.0.dist-info/WHEEL
TableProcessor-1.3.0.dist-info/top_level.txt
TableProcessor-1.3.0.dist-info/RECORD
